yt_dlp_plugins/extractor/getpot.py
yt_dlp_plugins/extractor/getpot_client.py
yt_dlp_get_pot-2024.8.18.2.dist-info/METADATA
yt_dlp_get_pot-2024.8.18.2.dist-info/WHEEL
yt_dlp_get_pot-2024.8.18.2.dist-info/licenses/LICENSE
yt_dlp_get_pot-2024.8.18.2.dist-info/RECORD
