Metadata-Version: 2.3
Name: yt-dlp-get-pot
Version: 2024.8.18.2
Author-email: coletdjnz <coletdjnz@protonmail.com>
License-Expression: Unlicense
License-File: LICENSE
Keywords: yt-dlp,yt-dlp-plugin
Requires-Python: >=3.8
